[{"kind":"link-migration-success","account_address":"0x0ae53cb6e3f42a79","path":"/public/flowTokenReceiver","capability_id":1},{"kind":"cadence-value-migration-success","account_address":"0x0ae53cb6e3f42a79","domain":"public","key":"flowTokenReceiver","migration":"LinkValueMigration"},{"kind":"link-migration-success","account_address":"0x0ae53cb6e3f42a79","path":"/public/flowTokenBalance","capability_id":2},{"kind":"cadence-value-migration-success","account_address":"0x0ae53cb6e3f42a79","domain":"public","key":"flowTokenBalance","migration":"LinkValueMigration"},{"kind":"link-migration-success","account_address":"0xee82856bf20e2aa6","path":"/public/flowTokenReceiver","capability_id":1},{"kind":"cadence-value-migration-success","account_address":"0xee82856bf20e2aa6","domain":"public","key":"flowTokenReceiver","migration":"LinkValueMigration"},{"kind":"link-migration-success","account_address":"0xee82856bf20e2aa6","path":"/public/flowTokenBalance","capability_id":2},{"kind":"cadence-value-migration-success","account_address":"0xee82856bf20e2aa6","domain":"public","key":"flowTokenBalance","migration":"LinkValueMigration"},{"kind":"link-migration-success","account_address":"0xf8d6e0586b0a20c7","path":"/private/flowStakingAdminEpochOperations","capability_id":1},{"kind":"cadence-value-migration-success","account_address":"0xf8d6e0586b0a20c7","domain":"private","key":"flowStakingAdminEpochOperations","migration":"LinkValueMigration"},{"kind":"link-migration-success","account_address":"0xf8d6e0586b0a20c7","path":"/private/lockedTokenAdmin","capability_id":2},{"kind":"cadence-value-migration-success","account_address":"0xf8d6e0586b0a20c7","domain":"private","key":"lockedTokenAdmin","migration":"LinkValueMigration"},{"kind":"link-migration-success","account_address":"0xf8d6e0586b0a20c7","path":"/private/flowDKGAdminEpochOperations","capability_id":3},{"kind":"cadence-value-migration-success","account_address":"0xf8d6e0586b0a20c7","domain":"private","key":"flowDKGAdminEpochOperations","migration":"LinkValueMigration"},{"kind":"link-migration-success","account_address":"0xe5a8b7f23e8b548f","path":"/public/flowTokenReceiver","capability_id":1},{"kind":"cadence-value-migration-success","account_address":"0xe5a8b7f23e8b548f","domain":"public","key":"flowTokenReceiver","migration":"LinkValueMigration"},{"kind":"link-migration-success","account_address":"0xe5a8b7f23e8b548f","path":"/public/flowTokenBalance","capability_id":2},{"kind":"cadence-value-migration-success","account_address":"0xe5a8b7f23e8b548f","domain":"public","key":"flowTokenBalance","migration":"LinkValueMigration"},{"kind":"link-migration-success","account_address":"0xf8d6e0586b0a20c7","path":"/private/flowQCAdminEpochOperations","capability_id":4},{"kind":"cadence-value-migration-success","account_address":"0xf8d6e0586b0a20c7","domain":"private","key":"flowQCAdminEpochOperations","migration":"LinkValueMigration"},{"kind":"link-migration-success","account_address":"0xf8d6e0586b0a20c7","path":"/public/flowTokenBalance","capability_id":5},{"kind":"cadence-value-migration-success","account_address":"0xf8d6e0586b0a20c7","domain":"public","key":"flowTokenBalance","migration":"LinkValueMigration"},{"kind":"link-migration-success","account_address":"0xf8d6e0586b0a20c7","path":"/public/flowTokenReceiver","capability_id":6},{"kind":"cadence-value-migration-success","account_address":"0xf8d6e0586b0a20c7","domain":"public","key":"flowTokenReceiver","migration":"LinkValueMigration"}]